betabinomial/__init__.py
betabinomial/betabinomial.py
betabinomial-0.0.2.dist-info/METADATA
betabinomial-0.0.2.dist-info/WHEEL
betabinomial-0.0.2.dist-info/top_level.txt
betabinomial-0.0.2.dist-info/RECORD
